discordpy_bypass/__init__.py
discordpy_bypass/discordpy_bypass.py
discordpy_bypass-1.7.dist-info/METADATA
discordpy_bypass-1.7.dist-info/WHEEL
discordpy_bypass-1.7.dist-info/top_level.txt
discordpy_bypass-1.7.dist-info/RECORD
