Metadata-Version: 2.1
Name: discordpy_bypass
Version: 1.7
Requires-Dist: requests
Requires-Dist: pywin32 ; sys_platform == "win32"
